py_compiler.py
app/__init__.py
app/__main__.py
app/application.py
test/__init__.py
test/test_compile.py
py_compileall-0.0.3.dist-info/LICENSE
py_compileall-0.0.3.dist-info/METADATA
py_compileall-0.0.3.dist-info/WHEEL
py_compileall-0.0.3.dist-info/entry_points.txt
py_compileall-0.0.3.dist-info/top_level.txt
py_compileall-0.0.3.dist-info/RECORD
